names_dataset/.DS_Store
names_dataset/__init__.py
names_dataset/nd_v4.py
names_dataset/v4/.DS_Store
names_dataset/v4/first_names.pkl
names_dataset/v4/last_names.pkl
names_dataset_pickle-1.0.1.dist-info/LICENSE
names_dataset_pickle-1.0.1.dist-info/METADATA
names_dataset_pickle-1.0.1.dist-info/WHEEL
names_dataset_pickle-1.0.1.dist-info/RECORD
