Metadata-Version: 2.1
Name: names-dataset-pickle
Version: 1.0.1
Summary: The python library to handle names
License: MIT
Author: satya-500
Author-email: satyabrata.swain@500apps.com
Requires-Python: >=3.9,<3.13
Classifier: License :: OSI Approved :: MIT License
Classifier: Programming Language :: Python :: 3
Classifier: Programming Language :: Python :: 3.9
Classifier: Programming Language :: Python :: 3.10
Classifier: Programming Language :: Python :: 3.11
Classifier: Programming Language :: Python :: 3.12
Requires-Dist: pycountry (>=24.6.1,<25.0.0)
